<?xml version="1.0" encoding="UTF-8"?>
<!DOCTYPE otml SYSTEM "otml.dtd">
<otml>
	<element>
		<station id="Dissertation_model_335" label="KUR">
			<position x="750.000000" y="635.000000"/>
		</station>
	</element>
	<element>
		<station id="Dissertation_model_756" label="JAR">
			<position x="830.000000" y="35.000000"/>
		</station>
	</element>
	<element>
		<station id="Dissertation_model_999" label="EKP">
			<position x="455.000000" y="355.000000"/>
		</station>
	</element>
	<element>
		<node station="Dissertation_model_335" profile="false">
			<position x="340.000000" y="740.000000"/>
				<leaf id="Dissertation_model_219" align="left"/>
				<leaf id="Dissertation_model_221" align="right"/>
		</node>
	</element>
	<element>
		<node station="Dissertation_model_335" profile="false">
			<position x="475.000000" y="740.000000"/>
				<leaf id="Dissertation_model_223" align="left"/>
				<leaf id="Dissertation_model_225" align="right"/>
		</node>
	</element>
	<element>
		<node station="Dissertation_model_335" profile="false">
			<position x="550.000000" y="740.000000"/>
				<leaf id="Dissertation_model_228" align="left"/>
				<leaf id="Dissertation_model_230" align="right"/>
		</node>
	</element>
	<element>
		<node station="Dissertation_model_335" profile="true">
			<position x="750.000000" y="740.000000"/>
				<leaf id="Dissertation_model_232" align="left"/>
				<leaf id="Dissertation_model_234" align="right"/>
		</node>
	</element>
	<element>
		<node station="Dissertation_model_335" profile="false">
			<position x="860.000000" y="740.000000"/>
				<leaf id="Dissertation_model_236" align="left"/>
				<leaf id="Dissertation_model_238" align="right"/>
		</node>
	</element>
	<element>
		<node station="Dissertation_model_335" profile="false">
			<position x="970.000000" y="740.000000"/>
				<leaf id="Dissertation_model_240" align="left"/>
				<leaf id="Dissertation_model_242" align="right"/>
		</node>
	</element>
	<element>
		<node station="Dissertation_model_335" profile="false">
			<position x="685.000000" y="690.000000"/>
				<leaf id="Dissertation_model_250" align="left"/>
				<leaf id="Dissertation_model_252" align="right"/>
		</node>
	</element>
	<element>
		<node station="Dissertation_model_335" profile="true">
			<position x="750.000000" y="690.000000"/>
				<leaf id="Dissertation_model_254" align="left"/>
				<leaf id="Dissertation_model_256" align="right"/>
		</node>
	</element>
	<element>
		<node station="Dissertation_model_335" profile="false">
			<position x="845.000000" y="690.000000"/>
				<leaf id="Dissertation_model_262" align="left"/>
				<leaf id="Dissertation_model_264" align="right"/>
		</node>
	</element>
	<element>
		<node station="Dissertation_model_335" profile="false">
			<position x="1045.000000" y="740.000000"/>
				<leaf id="Dissertation_model_267" align="left"/>
				<leaf id="Dissertation_model_269" align="right"/>
		</node>
	</element>
	<element>
		<node station="Dissertation_model_335" profile="false">
			<position x="520.000000" y="790.000000"/>
				<leaf id="Dissertation_model_271" align="left"/>
				<leaf id="Dissertation_model_273" align="right"/>
		</node>
	</element>
	<element>
		<node station="Dissertation_model_335" profile="false">
			<position x="605.000000" y="790.000000"/>
				<leaf id="Dissertation_model_276" align="left"/>
				<leaf id="Dissertation_model_278" align="right"/>
		</node>
	</element>
	<element>
		<node station="Dissertation_model_335" profile="true">
			<position x="750.000000" y="790.000000"/>
				<leaf id="Dissertation_model_280" align="left"/>
				<leaf id="Dissertation_model_282" align="right"/>
		</node>
	</element>
	<element>
		<node station="Dissertation_model_335" profile="false">
			<position x="870.000000" y="790.000000"/>
				<leaf id="Dissertation_model_284" align="left"/>
				<leaf id="Dissertation_model_286" align="right"/>
		</node>
	</element>
	<element>
		<node station="Dissertation_model_335" profile="false">
			<position x="980.000000" y="790.000000"/>
				<leaf id="Dissertation_model_288" align="left"/>
				<leaf id="Dissertation_model_290" align="right"/>
		</node>
	</element>
	<element>
		<node station="Dissertation_model_335" profile="false">
			<position x="1275.000000" y="740.000000"/>
				<leaf id="Dissertation_model_293" align="left"/>
				<leaf id="Dissertation_model_295" align="right"/>
		</node>
	</element>
	<element>
		<node station="Dissertation_model_335" profile="false">
			<position x="70.000000" y="740.000000"/>
				<leaf id="Dissertation_model_298" align="left"/>
				<leaf id="Dissertation_model_300" align="right"/>
		</node>
	</element>
	<element>
		<node station="Dissertation_model_335" profile="false">
			<position x="390.000000" y="790.000000"/>
				<leaf id="Dissertation_model_343" align="left"/>
				<leaf id="Dissertation_model_344" align="right"/>
		</node>
	</element>
	<element>
		<node station="Dissertation_model_335" profile="false">
			<position x="320.000000" y="790.000000"/>
				<leaf id="Dissertation_model_347" align="left"/>
				<leaf id="Dissertation_model_348" align="right"/>
		</node>
	</element>
	<element>
		<node station="Dissertation_model_335" profile="false">
			<position x="435.000000" y="790.000000"/>
				<leaf id="Dissertation_model_354" align="left"/>
				<leaf id="Dissertation_model_355" align="right"/>
		</node>
	</element>
	<element>
		<node station="Dissertation_model_335" profile="false">
			<position x="575.000000" y="840.000000"/>
				<leaf id="Dissertation_model_361" align="left"/>
				<leaf id="Dissertation_model_362" align="right"/>
		</node>
	</element>
	<element>
		<node station="Dissertation_model_335" profile="false">
			<position x="620.000000" y="840.000000"/>
				<leaf id="Dissertation_model_365" align="left"/>
				<leaf id="Dissertation_model_366" align="right"/>
		</node>
	</element>
	<element>
		<node station="Dissertation_model_335" profile="true">
			<position x="750.000000" y="840.000000"/>
				<leaf id="Dissertation_model_369" align="left"/>
				<leaf id="Dissertation_model_370" align="right"/>
		</node>
	</element>
	<element>
		<node station="Dissertation_model_335" profile="false">
			<position x="630.000000" y="890.000000"/>
				<leaf id="Dissertation_model_373" align="left"/>
				<leaf id="Dissertation_model_374" align="right"/>
		</node>
	</element>
	<element>
		<node station="Dissertation_model_335" profile="true">
			<position x="750.000000" y="890.000000"/>
				<leaf id="Dissertation_model_380" align="left"/>
				<leaf id="Dissertation_model_381" align="right"/>
		</node>
	</element>
	<element>
		<node station="Dissertation_model_335" profile="false">
			<position x="860.000000" y="890.000000"/>
				<leaf id="Dissertation_model_384" align="left"/>
				<leaf id="Dissertation_model_385" align="right"/>
		</node>
	</element>
	<element>
		<node station="Dissertation_model_335" profile="false">
			<position x="875.000000" y="840.000000"/>
				<leaf id="Dissertation_model_388" align="left"/>
				<leaf id="Dissertation_model_389" align="right"/>
		</node>
	</element>
	<element>
		<node station="Dissertation_model_335" profile="false">
			<position x="625.000000" y="740.000000"/>
				<leaf id="Dissertation_model_398" align="left"/>
				<leaf id="Dissertation_model_399" align="right"/>
		</node>
	</element>
	<element>
		<node station="Dissertation_model_335" profile="false">
			<position x="650.000000" y="790.000000"/>
				<leaf id="Dissertation_model_404" align="left"/>
				<leaf id="Dissertation_model_405" align="right"/>
		</node>
	</element>
	<element>
		<node station="Dissertation_model_335" profile="false">
			<position x="675.000000" y="740.000000"/>
				<leaf id="Dissertation_model_408" align="left"/>
				<leaf id="Dissertation_model_409" align="right"/>
		</node>
	</element>
	<element>
		<node station="Dissertation_model_335" profile="false">
			<position x="920.000000" y="840.000000"/>
				<leaf id="Dissertation_model_423" align="left"/>
				<leaf id="Dissertation_model_424" align="right"/>
		</node>
	</element>
	<element>
		<node station="Dissertation_model_335" profile="false">
			<position x="905.000000" y="790.000000"/>
				<leaf id="Dissertation_model_432" align="left"/>
				<leaf id="Dissertation_model_433" align="right"/>
		</node>
	</element>
	<element>
		<node station="Dissertation_model_335" profile="false">
			<position x="900.000000" y="740.000000"/>
				<leaf id="Dissertation_model_442" align="left"/>
				<leaf id="Dissertation_model_443" align="right"/>
		</node>
	</element>
	<element>
		<node station="Dissertation_model_335" profile="false">
			<position x="1090.000000" y="790.000000"/>
				<leaf id="Dissertation_model_452" align="left"/>
				<leaf id="Dissertation_model_453" align="right"/>
		</node>
	</element>
	<element>
		<node station="Dissertation_model_335" profile="false">
			<position x="1125.000000" y="790.000000"/>
				<leaf id="Dissertation_model_456" align="left"/>
				<leaf id="Dissertation_model_457" align="right"/>
		</node>
	</element>
	<element>
		<node station="Dissertation_model_335" profile="false">
			<position x="1190.000000" y="790.000000"/>
				<leaf id="Dissertation_model_460" align="left"/>
				<leaf id="Dissertation_model_461" align="right"/>
		</node>
	</element>
	<element>
		<node station="Dissertation_model_335" profile="false">
			<position x="1170.000000" y="740.000000"/>
				<leaf id="Dissertation_model_464" align="left"/>
				<leaf id="Dissertation_model_465" align="right"/>
		</node>
	</element>
	<element>
		<node station="Dissertation_model_756" profile="false">
			<position x="575.000000" y="130.000000"/>
				<leaf id="Dissertation_model_688" align="left"/>
				<leaf id="Dissertation_model_690" align="right"/>
		</node>
	</element>
	<element>
		<node station="Dissertation_model_756" profile="false">
			<position x="645.000000" y="130.000000"/>
				<leaf id="Dissertation_model_692" align="left"/>
				<leaf id="Dissertation_model_694" align="right"/>
		</node>
	</element>
	<element>
		<node station="Dissertation_model_756" profile="false">
			<position x="700.000000" y="130.000000"/>
				<leaf id="Dissertation_model_696" align="left"/>
				<leaf id="Dissertation_model_698" align="right"/>
		</node>
	</element>
	<element>
		<node station="Dissertation_model_756" profile="true">
			<position x="830.000000" y="130.000000"/>
				<leaf id="Dissertation_model_701" align="left"/>
				<leaf id="Dissertation_model_703" align="right"/>
		</node>
	</element>
	<element>
		<node station="Dissertation_model_756" profile="false">
			<position x="955.000000" y="130.000000"/>
				<leaf id="Dissertation_model_705" align="left"/>
				<leaf id="Dissertation_model_707" align="right"/>
		</node>
	</element>
	<element>
		<node station="Dissertation_model_756" profile="false">
			<position x="1020.000000" y="130.000000"/>
				<leaf id="Dissertation_model_709" align="left"/>
				<leaf id="Dissertation_model_711" align="right"/>
		</node>
	</element>
	<element>
		<node station="Dissertation_model_756" profile="false">
			<position x="705.000000" y="90.000000"/>
				<leaf id="Dissertation_model_714" align="left"/>
				<leaf id="Dissertation_model_716" align="right"/>
		</node>
	</element>
	<element>
		<node station="Dissertation_model_756" profile="true">
			<position x="830.000000" y="90.000000"/>
				<leaf id="Dissertation_model_719" align="left"/>
				<leaf id="Dissertation_model_721" align="right"/>
		</node>
	</element>
	<element>
		<node station="Dissertation_model_756" profile="false">
			<position x="955.000000" y="90.000000"/>
				<leaf id="Dissertation_model_723" align="left"/>
				<leaf id="Dissertation_model_725" align="right"/>
		</node>
	</element>
	<element>
		<node station="Dissertation_model_756" profile="false">
			<position x="1085.000000" y="130.000000"/>
				<leaf id="Dissertation_model_728" align="left"/>
				<leaf id="Dissertation_model_730" align="right"/>
		</node>
	</element>
	<element>
		<node station="Dissertation_model_756" profile="false">
			<position x="685.000000" y="170.000000"/>
				<leaf id="Dissertation_model_732" align="left"/>
				<leaf id="Dissertation_model_734" align="right"/>
		</node>
	</element>
	<element>
		<node station="Dissertation_model_756" profile="true">
			<position x="830.000000" y="170.000000"/>
				<leaf id="Dissertation_model_737" align="left"/>
				<leaf id="Dissertation_model_739" align="right"/>
		</node>
	</element>
	<element>
		<node station="Dissertation_model_756" profile="false">
			<position x="1010.000000" y="170.000000"/>
				<leaf id="Dissertation_model_741" align="left"/>
				<leaf id="Dissertation_model_743" align="right"/>
		</node>
	</element>
	<element>
		<node station="Dissertation_model_756" profile="false">
			<position x="1340.000000" y="130.000000"/>
				<leaf id="Dissertation_model_746" align="left"/>
				<leaf id="Dissertation_model_748" align="right"/>
		</node>
	</element>
	<element>
		<node station="Dissertation_model_756" profile="false">
			<position x="385.000000" y="130.000000"/>
				<leaf id="Dissertation_model_751" align="left"/>
				<leaf id="Dissertation_model_753" align="right"/>
		</node>
	</element>
	<element>
		<node station="Dissertation_model_335" profile="false">
			<position x="455.000000" y="765.000000"/>
				<leaf id="Dissertation_model_810" align="left"/>
				<leaf id="Dissertation_model_811" align="right"/>
		</node>
	</element>
	<element>
		<node station="Dissertation_model_335" profile="false">
			<position x="365.000000" y="765.000000"/>
				<leaf id="Dissertation_model_826" align="left"/>
				<leaf id="Dissertation_model_827" align="right"/>
		</node>
	</element>
	<element>
		<node station="Dissertation_model_335" profile="false">
			<position x="580.000000" y="765.000000"/>
				<leaf id="Dissertation_model_839" align="left"/>
				<leaf id="Dissertation_model_840" align="right"/>
		</node>
	</element>
	<element>
		<node station="Dissertation_model_335" profile="false">
			<position x="935.000000" y="765.000000"/>
				<leaf id="Dissertation_model_854" align="left"/>
				<leaf id="Dissertation_model_855" align="right"/>
		</node>
	</element>
	<element>
		<node station="Dissertation_model_335" profile="false">
			<position x="1065.000000" y="765.000000"/>
				<leaf id="Dissertation_model_868" align="left"/>
				<leaf id="Dissertation_model_869" align="right"/>
		</node>
	</element>
	<element>
		<node station="Dissertation_model_335" profile="false">
			<position x="1150.000000" y="765.000000"/>
				<leaf id="Dissertation_model_886" align="left"/>
				<leaf id="Dissertation_model_887" align="right"/>
		</node>
	</element>
	<element>
		<node station="Dissertation_model_999" profile="false">
			<position x="200.000000" y="445.000000"/>
				<leaf id="Dissertation_model_931" align="left"/>
				<leaf id="Dissertation_model_933" align="right"/>
		</node>
	</element>
	<element>
		<node station="Dissertation_model_999" profile="false">
			<position x="270.000000" y="445.000000"/>
				<leaf id="Dissertation_model_935" align="left"/>
				<leaf id="Dissertation_model_937" align="right"/>
		</node>
	</element>
	<element>
		<node station="Dissertation_model_999" profile="false">
			<position x="325.000000" y="445.000000"/>
				<leaf id="Dissertation_model_939" align="left"/>
				<leaf id="Dissertation_model_941" align="right"/>
		</node>
	</element>
	<element>
		<node station="Dissertation_model_999" profile="true">
			<position x="455.000000" y="445.000000"/>
				<leaf id="Dissertation_model_944" align="left"/>
				<leaf id="Dissertation_model_946" align="right"/>
		</node>
	</element>
	<element>
		<node station="Dissertation_model_999" profile="false">
			<position x="590.000000" y="445.000000"/>
				<leaf id="Dissertation_model_952" align="left"/>
				<leaf id="Dissertation_model_954" align="right"/>
		</node>
	</element>
	<element>
		<node station="Dissertation_model_999" profile="false">
			<position x="330.000000" y="405.000000"/>
				<leaf id="Dissertation_model_957" align="left"/>
				<leaf id="Dissertation_model_959" align="right"/>
		</node>
	</element>
	<element>
		<node station="Dissertation_model_999" profile="true">
			<position x="455.000000" y="405.000000"/>
				<leaf id="Dissertation_model_962" align="left"/>
				<leaf id="Dissertation_model_964" align="right"/>
		</node>
	</element>
	<element>
		<node station="Dissertation_model_999" profile="false">
			<position x="580.000000" y="405.000000"/>
				<leaf id="Dissertation_model_966" align="left"/>
				<leaf id="Dissertation_model_968" align="right"/>
		</node>
	</element>
	<element>
		<node station="Dissertation_model_999" profile="false">
			<position x="710.000000" y="445.000000"/>
				<leaf id="Dissertation_model_971" align="left"/>
				<leaf id="Dissertation_model_973" align="right"/>
		</node>
	</element>
	<element>
		<node station="Dissertation_model_999" profile="false">
			<position x="315.000000" y="485.000000"/>
				<leaf id="Dissertation_model_975" align="left"/>
				<leaf id="Dissertation_model_977" align="right"/>
		</node>
	</element>
	<element>
		<node station="Dissertation_model_999" profile="true">
			<position x="455.000000" y="485.000000"/>
				<leaf id="Dissertation_model_980" align="left"/>
				<leaf id="Dissertation_model_982" align="right"/>
		</node>
	</element>
	<element>
		<node station="Dissertation_model_999" profile="false">
			<position x="635.000000" y="485.000000"/>
				<leaf id="Dissertation_model_984" align="left"/>
				<leaf id="Dissertation_model_986" align="right"/>
		</node>
	</element>
	<element>
		<node station="Dissertation_model_999" profile="false">
			<position x="825.000000" y="445.000000"/>
				<leaf id="Dissertation_model_989" align="left"/>
				<leaf id="Dissertation_model_991" align="right"/>
		</node>
	</element>
	<element>
		<node station="Dissertation_model_999" profile="false">
			<position x="130.000000" y="445.000000"/>
				<leaf id="Dissertation_model_994" align="left"/>
				<leaf id="Dissertation_model_996" align="right"/>
		</node>
	</element>
	<element>
		<node>
			<position x="905.000000" y="445.000000"/>
				<leaf id="Dissertation_model_1032" align="left"/>
				<leaf id="Dissertation_model_1033" align="right"/>
		</node>
	</element>
	<element>
		<node>
			<position x="1045.000000" y="445.000000"/>
				<leaf id="Dissertation_model_1040" align="left"/>
				<leaf id="Dissertation_model_1041" align="right"/>
		</node>
	</element>
	<element>
		<node>
			<position x="1155.000000" y="445.000000"/>
				<leaf id="Dissertation_model_1044" align="left"/>
				<leaf id="Dissertation_model_1045" align="right"/>
		</node>
	</element>
	<element>
		<node>
			<position x="1250.000000" y="445.000000"/>
				<leaf id="Dissertation_model_1048" align="left"/>
				<leaf id="Dissertation_model_1049" align="right"/>
		</node>
	</element>
	<element>
		<node>
			<position x="635.000000" y="300.000000"/>
				<leaf id="Dissertation_model_1082" align="left"/>
				<leaf id="Dissertation_model_1083" align="right"/>
		</node>
	</element>
	<element>
		<node>
			<position x="695.000000" y="300.000000"/>
				<leaf id="Dissertation_model_1086" align="left"/>
				<leaf id="Dissertation_model_1087" align="right"/>
		</node>
	</element>
	<element>
		<node>
			<position x="810.000000" y="300.000000"/>
				<leaf id="Dissertation_model_1090" align="left"/>
				<leaf id="Dissertation_model_1091" align="right"/>
		</node>
	</element>
	<element>
		<node>
			<position x="875.000000" y="300.000000"/>
				<leaf id="Dissertation_model_1094" align="left"/>
				<leaf id="Dissertation_model_1095" align="right"/>
		</node>
	</element>
	<element>
		<node>
			<position x="995.000000" y="300.000000"/>
				<leaf id="Dissertation_model_1098" align="left"/>
				<leaf id="Dissertation_model_1099" align="right"/>
		</node>
	</element>
	<element>
		<node>
			<position x="220.000000" y="130.000000"/>
				<leaf id="Dissertation_model_1118" align="left"/>
				<leaf id="Dissertation_model_1119" align="right"/>
		</node>
	</element>
	<element>
		<node>
			<position x="575.000000" y="300.000000"/>
				<leaf id="Dissertation_model_1122" align="left"/>
				<leaf id="Dissertation_model_1123" align="right"/>
		</node>
	</element>
	<element>
		<node>
			<position x="515.000000" y="300.000000"/>
				<leaf id="Dissertation_model_1126" align="left"/>
				<leaf id="Dissertation_model_1127" align="right"/>
		</node>
	</element>
	<element>
		<node>
			<position x="405.000000" y="300.000000"/>
				<leaf id="Dissertation_model_1130" align="left"/>
				<leaf id="Dissertation_model_1131" align="right"/>
		</node>
	</element>
	<element>
		<node>
			<position x="285.000000" y="300.000000"/>
				<leaf id="Dissertation_model_1134" align="left"/>
				<leaf id="Dissertation_model_1135" align="right"/>
		</node>
	</element>
	<element>
		<node>
			<position x="225.000000" y="300.000000"/>
				<leaf id="Dissertation_model_1138" align="left"/>
				<leaf id="Dissertation_model_1139" align="right"/>
		</node>
	</element>
	<element>
		<node>
			<position x="115.000000" y="300.000000"/>
				<leaf id="Dissertation_model_1142" align="left"/>
				<leaf id="Dissertation_model_1143" align="right"/>
		</node>
	</element>
	<element>
		<node>
			<position x="240.000000" y="595.000000"/>
				<leaf id="Dissertation_model_1167" align="left"/>
				<leaf id="Dissertation_model_1168" align="right"/>
		</node>
	</element>
	<element>
		<node>
			<position x="295.000000" y="595.000000"/>
				<leaf id="Dissertation_model_1171" align="left"/>
				<leaf id="Dissertation_model_1172" align="right"/>
		</node>
	</element>
	<element>
		<node>
			<position x="355.000000" y="595.000000"/>
				<leaf id="Dissertation_model_1175" align="left"/>
				<leaf id="Dissertation_model_1176" align="right"/>
		</node>
	</element>
	<element>
		<node>
			<position x="490.000000" y="595.000000"/>
				<leaf id="Dissertation_model_1179" align="left"/>
				<leaf id="Dissertation_model_1180" align="right"/>
		</node>
	</element>
	<element>
		<node>
			<position x="555.000000" y="595.000000"/>
				<leaf id="Dissertation_model_1183" align="left"/>
				<leaf id="Dissertation_model_1184" align="right"/>
		</node>
	</element>
	<element>
		<node>
			<position x="615.000000" y="595.000000"/>
				<leaf id="Dissertation_model_1187" align="left"/>
				<leaf id="Dissertation_model_1188" align="right"/>
		</node>
	</element>
	<element>
		<node>
			<position x="675.000000" y="595.000000"/>
				<leaf id="Dissertation_model_1191" align="left"/>
				<leaf id="Dissertation_model_1192" align="right"/>
		</node>
	</element>
	<element>
		<node>
			<position x="795.000000" y="595.000000"/>
				<leaf id="Dissertation_model_1195" align="left"/>
				<leaf id="Dissertation_model_1196" align="right"/>
		</node>
	</element>
	<element>
		<node>
			<position x="860.000000" y="595.000000"/>
				<leaf id="Dissertation_model_1199" align="left"/>
				<leaf id="Dissertation_model_1200" align="right"/>
		</node>
	</element>
	<element>
		<node>
			<position x="925.000000" y="595.000000"/>
				<leaf id="Dissertation_model_1203" align="left"/>
				<leaf id="Dissertation_model_1204" align="right"/>
		</node>
	</element>
	<element>
		<node>
			<position x="995.000000" y="595.000000"/>
				<leaf id="Dissertation_model_1207" align="left"/>
				<leaf id="Dissertation_model_1208" align="right"/>
		</node>
	</element>
	<element>
		<node>
			<position x="1060.000000" y="595.000000"/>
				<leaf id="Dissertation_model_1211" align="left"/>
				<leaf id="Dissertation_model_1212" align="right"/>
		</node>
	</element>
	<element>
		<node>
			<position x="1120.000000" y="595.000000"/>
				<leaf id="Dissertation_model_1215" align="left"/>
				<leaf id="Dissertation_model_1216" align="right"/>
		</node>
	</element>
	<element>
		<node>
			<position x="1175.000000" y="595.000000"/>
				<leaf id="Dissertation_model_1219" align="left"/>
				<leaf id="Dissertation_model_1220" align="right"/>
		</node>
	</element>
	<element>
		<node>
			<position x="1290.000000" y="595.000000"/>
				<leaf id="Dissertation_model_1275" align="right"/>
				<leaf id="Dissertation_model_1276" align="left"/>
		</node>
	</element>
	<element>
		<node>
			<position x="120.000000" y="595.000000"/>
				<leaf id="Dissertation_model_1299" align="right"/>
				<leaf id="Dissertation_model_1300" align="left"/>
		</node>
	</element>
	<element>
		<node>
			<position x="165.000000" y="130.000000"/>
				<leaf id="Dissertation_model_1311" align="right"/>
				<leaf id="Dissertation_model_1312" align="left"/>
		</node>
	</element>
	<element>
		<node>
			<position x="950.000000" y="445.000000"/>
				<leaf id="Dissertation_model_1325" align="left"/>
				<leaf id="Dissertation_model_1326" align="right"/>
		</node>
	</element>
	<element>
		<node>
			<position x="1120.000000" y="300.000000"/>
				<leaf id="Dissertation_model_1366" align="left"/>
				<leaf id="Dissertation_model_1368" align="right"/>
		</node>
	</element>
	<element>
		<node>
			<position x="1240.000000" y="300.000000"/>
				<leaf id="Dissertation_model_1374" align="left"/>
				<leaf id="Dissertation_model_1376" align="right"/>
		</node>
	</element>
	<element>
		<node>
			<position x="1295.000000" y="300.000000"/>
				<leaf id="Dissertation_model_1411" align="left"/>
				<leaf id="Dissertation_model_1412" align="right"/>
		</node>
	</element>
	<element>
		<node station="Dissertation_model_999" profile="false">
			<position x="660.000000" y="445.000000"/>
				<leaf id="Dissertation_model_1428" align="left"/>
				<leaf id="Dissertation_model_1429" align="right"/>
		</node>
	</element>
	<element>
		<node station="Dissertation_model_335" profile="false">
			<position x="655.000000" y="840.000000"/>
				<leaf id="Dissertation_model_1459" align="left"/>
				<leaf id="Dissertation_model_1460" align="right"/>
		</node>
	</element>
	<element>
		<node station="Dissertation_model_335" profile="false">
			<position x="685.000000" y="790.000000"/>
				<leaf id="Dissertation_model_1471" align="left"/>
				<leaf id="Dissertation_model_1472" align="right"/>
		</node>
	</element>
	<element>
		<node station="Dissertation_model_335" profile="false">
			<position x="705.000000" y="740.000000"/>
				<leaf id="Dissertation_model_1483" align="left"/>
				<leaf id="Dissertation_model_1484" align="right"/>
		</node>
	</element>
	<element>
		<node station="Dissertation_model_335" profile="false">
			<position x="715.000000" y="690.000000"/>
				<leaf id="Dissertation_model_1495" align="left"/>
				<leaf id="Dissertation_model_1496" align="right"/>
		</node>
	</element>
	<element>
		<node station="Dissertation_model_335" profile="false">
			<position x="815.000000" y="690.000000"/>
				<leaf id="Dissertation_model_1507" align="left"/>
				<leaf id="Dissertation_model_1508" align="right"/>
		</node>
	</element>
	<element>
		<node station="Dissertation_model_335" profile="false">
			<position x="830.000000" y="740.000000"/>
				<leaf id="Dissertation_model_1519" align="left"/>
				<leaf id="Dissertation_model_1520" align="right"/>
		</node>
	</element>
	<element>
		<node station="Dissertation_model_335" profile="false">
			<position x="840.000000" y="790.000000"/>
				<leaf id="Dissertation_model_1531" align="left"/>
				<leaf id="Dissertation_model_1532" align="right"/>
		</node>
	</element>
	<element>
		<node station="Dissertation_model_335" profile="false">
			<position x="840.000000" y="840.000000"/>
				<leaf id="Dissertation_model_1543" align="left"/>
				<leaf id="Dissertation_model_1544" align="right"/>
		</node>
	</element>
	<element>
		<node station="Dissertation_model_335" profile="false">
			<position x="830.000000" y="890.000000"/>
				<leaf id="Dissertation_model_1555" align="left"/>
				<leaf id="Dissertation_model_1556" align="right"/>
		</node>
	</element>
	<element>
		<node station="Dissertation_model_335" profile="false">
			<position x="800.000000" y="890.000000"/>
				<leaf id="Dissertation_model_1868" align="left"/>
				<leaf id="Dissertation_model_1869" align="right"/>
		</node>
	</element>
	<element>
		<node station="Dissertation_model_335" profile="false">
			<position x="805.000000" y="840.000000"/>
				<leaf id="Dissertation_model_1880" align="left"/>
				<leaf id="Dissertation_model_1881" align="right"/>
		</node>
	</element>
	<element>
		<node station="Dissertation_model_335" profile="false">
			<position x="810.000000" y="790.000000"/>
				<leaf id="Dissertation_model_1892" align="left"/>
				<leaf id="Dissertation_model_1893" align="right"/>
		</node>
	</element>
	<element>
		<node station="Dissertation_model_335" profile="false">
			<position x="800.000000" y="740.000000"/>
				<leaf id="Dissertation_model_1904" align="left"/>
				<leaf id="Dissertation_model_1905" align="right"/>
		</node>
	</element>
	<element>
		<node station="Dissertation_model_335" profile="false">
			<position x="785.000000" y="690.000000"/>
				<leaf id="Dissertation_model_1916" align="left"/>
				<leaf id="Dissertation_model_1917" align="right"/>
		</node>
	</element>
	<element>
		<node station="Dissertation_model_999" profile="false">
			<position x="355.000000" y="535.000000"/>
				<leaf id="Dissertation_model_1938" align="left"/>
				<leaf id="Dissertation_model_1939" align="right"/>
		</node>
	</element>
	<element>
		<node station="Dissertation_model_999" profile="false">
			<position x="400.000000" y="535.000000"/>
				<leaf id="Dissertation_model_1942" align="left"/>
				<leaf id="Dissertation_model_1943" align="right"/>
		</node>
	</element>
	<element>
		<node station="Dissertation_model_999" profile="false">
			<position x="295.000000" y="535.000000"/>
				<leaf id="Dissertation_model_1947" align="left"/>
				<leaf id="Dissertation_model_1948" align="right"/>
		</node>
	</element>
	<element>
		<node station="Dissertation_model_999" profile="false">
			<position x="270.000000" y="485.000000"/>
				<leaf id="Dissertation_model_1966" align="left"/>
				<leaf id="Dissertation_model_1967" align="right"/>
		</node>
	</element>
	<element>
		<node station="Dissertation_model_999" profile="false">
			<position x="320.000000" y="515.000000"/>
				<leaf id="Dissertation_model_1975" align="left"/>
				<leaf id="Dissertation_model_1976" align="right"/>
		</node>
	</element>
	<element>
		<node>
			<position x="180.000000" y="595.000000"/>
				<leaf id="Dissertation_model_1994" align="left"/>
				<leaf id="Dissertation_model_1995" align="right"/>
		</node>
	</element>
	<element>
		<node>
			<position x="1235.000000" y="595.000000"/>
				<leaf id="Dissertation_model_2006" align="left"/>
				<leaf id="Dissertation_model_2007" align="right"/>
		</node>
	</element>
	<element>
		<node>
			<position x="735.000000" y="595.000000"/>
				<leaf id="Dissertation_model_2018" align="left"/>
				<leaf id="Dissertation_model_2019" align="right"/>
		</node>
	</element>
	<element>
		<node>
			<position x="420.000000" y="595.000000"/>
				<leaf id="Dissertation_model_2030" align="left"/>
				<leaf id="Dissertation_model_2031" align="right"/>
		</node>
	</element>
	<element>
		<node station="Dissertation_model_999" profile="false">
			<position x="100.000000" y="445.000000"/>
				<leaf id="Dissertation_model_2078" align="left"/>
				<leaf id="Dissertation_model_2079" align="right"/>
		</node>
	</element>
	<element>
		<node>
			<position x="1290.000000" y="445.000000"/>
				<leaf id="Dissertation_model_2110" align="left"/>
				<leaf id="Dissertation_model_2111" align="right"/>
		</node>
	</element>
	<element>
		<node>
			<position x="120.000000" y="130.000000"/>
				<leaf id="Dissertation_model_2122" align="left"/>
				<leaf id="Dissertation_model_2123" align="right"/>
		</node>
	</element>
	<element>
		<node station="Dissertation_model_756" profile="false">
			<position x="635.000000" y="170.000000"/>
				<leaf id="Dissertation_model_2137" align="right"/>
				<leaf id="Dissertation_model_2138" align="left"/>
		</node>
	</element>
	<element>
		<node>
			<position x="705.000000" y="215.000000"/>
				<leaf id="Dissertation_model_2149" align="left"/>
				<leaf id="Dissertation_model_2150" align="right"/>
		</node>
	</element>
	<element>
		<node>
			<position x="755.000000" y="215.000000"/>
				<leaf id="Dissertation_model_2154" align="left"/>
				<leaf id="Dissertation_model_2155" align="right"/>
		</node>
	</element>
	<element>
		<node>
			<position x="640.000000" y="215.000000"/>
				<leaf id="Dissertation_model_2158" align="left"/>
				<leaf id="Dissertation_model_2159" align="right"/>
		</node>
	</element>
	<element>
		<node station="Dissertation_model_756" profile="false">
			<position x="670.000000" y="195.000000"/>
				<leaf id="Dissertation_model_2179" align="left"/>
				<leaf id="Dissertation_model_2180" align="right"/>
		</node>
	</element>
	<element>
		<node>
			<position x="865.000000" y="445.000000"/>
				<leaf id="Dissertation_model_2192" align="left"/>
				<leaf id="Dissertation_model_2193" align="right"/>
		</node>
	</element>
	<element>
		<node>
			<position x="995.000000" y="445.000000"/>
				<leaf id="Dissertation_model_2216" align="left"/>
				<leaf id="Dissertation_model_2217" align="right"/>
		</node>
	</element>
	<element>
		<node>
			<position x="1100.000000" y="445.000000"/>
				<leaf id="Dissertation_model_2228" align="left"/>
				<leaf id="Dissertation_model_2229" align="right"/>
		</node>
	</element>
	<element>
		<node>
			<position x="1200.000000" y="445.000000"/>
				<leaf id="Dissertation_model_2240" align="left"/>
				<leaf id="Dissertation_model_2241" align="right"/>
		</node>
	</element>
	<element>
		<node>
			<position x="1180.000000" y="300.000000"/>
				<leaf id="Dissertation_model_2252" align="left"/>
				<leaf id="Dissertation_model_2253" align="right"/>
		</node>
	</element>
	<element>
		<node>
			<position x="1060.000000" y="300.000000"/>
				<leaf id="Dissertation_model_2276" align="left"/>
				<leaf id="Dissertation_model_2277" align="right"/>
		</node>
	</element>
	<element>
		<node>
			<position x="935.000000" y="300.000000"/>
				<leaf id="Dissertation_model_2288" align="left"/>
				<leaf id="Dissertation_model_2289" align="right"/>
		</node>
	</element>
	<element>
		<node>
			<position x="750.000000" y="300.000000"/>
				<leaf id="Dissertation_model_2300" align="left"/>
				<leaf id="Dissertation_model_2301" align="right"/>
		</node>
	</element>
	<element>
		<node>
			<position x="170.000000" y="300.000000"/>
				<leaf id="Dissertation_model_2312" align="left"/>
				<leaf id="Dissertation_model_2313" align="right"/>
		</node>
	</element>
	<element>
		<node>
			<position x="275.000000" y="130.000000"/>
				<leaf id="Dissertation_model_2324" align="left"/>
				<leaf id="Dissertation_model_2325" align="right"/>
		</node>
	</element>
	<element>
		<node>
			<position x="330.000000" y="130.000000"/>
				<leaf id="Dissertation_model_2336" align="left"/>
				<leaf id="Dissertation_model_2337" align="right"/>
		</node>
	</element>
	<element>
		<node>
			<position x="345.000000" y="300.000000"/>
				<leaf id="Dissertation_model_2357" align="left"/>
				<leaf id="Dissertation_model_2358" align="right"/>
		</node>
	</element>
	<element>
		<node>
			<position x="460.000000" y="300.000000"/>
				<leaf id="Dissertation_model_2369" align="left"/>
				<leaf id="Dissertation_model_2370" align="right"/>
		</node>
	</element>
	<element>
		<node station="Dissertation_model_999" profile="false">
			<position x="350.000000" y="485.000000"/>
				<leaf id="Dissertation_model_2384" align="left"/>
				<leaf id="Dissertation_model_2385" align="right"/>
		</node>
	</element>
	<element>
		<node station="Dissertation_model_999" profile="false">
			<position x="600.000000" y="485.000000"/>
				<leaf id="Dissertation_model_2396" align="left"/>
				<leaf id="Dissertation_model_2397" align="right"/>
		</node>
	</element>
	<element>
		<node station="Dissertation_model_999" profile="false">
			<position x="570.000000" y="485.000000"/>
				<leaf id="Dissertation_model_2408" align="left"/>
				<leaf id="Dissertation_model_2409" align="right"/>
		</node>
	</element>
	<element>
		<node station="Dissertation_model_999" profile="false">
			<position x="400.000000" y="445.000000"/>
				<leaf id="Dissertation_model_2424" align="left"/>
				<leaf id="Dissertation_model_2425" align="right"/>
		</node>
	</element>
	<element>
		<node station="Dissertation_model_999" profile="false">
			<position x="365.000000" y="445.000000"/>
				<leaf id="Dissertation_model_2436" align="left"/>
				<leaf id="Dissertation_model_2437" align="right"/>
		</node>
	</element>
	<element>
		<node station="Dissertation_model_999" profile="false">
			<position x="555.000000" y="445.000000"/>
				<leaf id="Dissertation_model_2448" align="left"/>
				<leaf id="Dissertation_model_2449" align="right"/>
		</node>
	</element>
	<element>
		<node station="Dissertation_model_999" profile="false">
			<position x="365.000000" y="405.000000"/>
				<leaf id="Dissertation_model_2460" align="left"/>
				<leaf id="Dissertation_model_2461" align="right"/>
		</node>
	</element>
	<element>
		<node station="Dissertation_model_999" profile="false">
			<position x="545.000000" y="405.000000"/>
				<leaf id="Dissertation_model_2472" align="left"/>
				<leaf id="Dissertation_model_2473" align="right"/>
		</node>
	</element>
	<element>
		<node station="Dissertation_model_999" profile="false">
			<position x="510.000000" y="405.000000"/>
				<leaf id="Dissertation_model_2484" align="left"/>
				<leaf id="Dissertation_model_2485" align="right"/>
		</node>
	</element>
	<element>
		<node station="Dissertation_model_756" profile="false">
			<position x="730.000000" y="170.000000"/>
				<leaf id="Dissertation_model_2504" align="left"/>
				<leaf id="Dissertation_model_2505" align="right"/>
		</node>
	</element>
	<element>
		<node station="Dissertation_model_756" profile="false">
			<position x="970.000000" y="170.000000"/>
				<leaf id="Dissertation_model_2516" align="left"/>
				<leaf id="Dissertation_model_2517" align="right"/>
		</node>
	</element>
	<element>
		<node station="Dissertation_model_756" profile="false">
			<position x="925.000000" y="170.000000"/>
				<leaf id="Dissertation_model_2528" align="left"/>
				<leaf id="Dissertation_model_2529" align="right"/>
		</node>
	</element>
	<element>
		<node station="Dissertation_model_756" profile="false">
			<position x="740.000000" y="130.000000"/>
				<leaf id="Dissertation_model_2540" align="left"/>
				<leaf id="Dissertation_model_2541" align="right"/>
		</node>
	</element>
	<element>
		<node station="Dissertation_model_756" profile="false">
			<position x="780.000000" y="130.000000"/>
				<leaf id="Dissertation_model_2552" align="left"/>
				<leaf id="Dissertation_model_2553" align="right"/>
		</node>
	</element>
	<element>
		<node station="Dissertation_model_756" profile="false">
			<position x="910.000000" y="130.000000"/>
				<leaf id="Dissertation_model_2564" align="left"/>
				<leaf id="Dissertation_model_2565" align="right"/>
		</node>
	</element>
	<element>
		<node station="Dissertation_model_756" profile="false">
			<position x="750.000000" y="90.000000"/>
				<leaf id="Dissertation_model_2576" align="left"/>
				<leaf id="Dissertation_model_2577" align="right"/>
		</node>
	</element>
	<element>
		<node station="Dissertation_model_756" profile="false">
			<position x="920.000000" y="90.000000"/>
				<leaf id="Dissertation_model_2588" align="left"/>
				<leaf id="Dissertation_model_2589" align="right"/>
		</node>
	</element>
	<element>
		<node station="Dissertation_model_756" profile="false">
			<position x="880.000000" y="90.000000"/>
				<leaf id="Dissertation_model_2600" align="left"/>
				<leaf id="Dissertation_model_2601" align="right"/>
		</node>
	</element>
	<element>
		<node station="Dissertation_model_756" profile="false">
			<position x="450.000000" y="130.000000"/>
				<leaf id="Dissertation_model_2654" align="left"/>
				<leaf id="Dissertation_model_2655" align="right"/>
		</node>
	</element>
	<element>
		<node station="Dissertation_model_756" profile="false">
			<position x="1170.000000" y="130.000000"/>
				<leaf id="Dissertation_model_2672" align="left"/>
				<leaf id="Dissertation_model_2673" align="right"/>
		</node>
	</element>
	<element>
		<node station="Dissertation_model_756" profile="false">
			<position x="1245.000000" y="130.000000"/>
				<leaf id="Dissertation_model_2684" align="left"/>
				<leaf id="Dissertation_model_2685" align="right"/>
		</node>
	</element>
	<element>
		<node station="Dissertation_model_335" profile="false">
			<position x="155.000000" y="740.000000"/>
				<leaf id="Dissertation_model_2700" align="left"/>
				<leaf id="Dissertation_model_2701" align="right"/>
		</node>
	</element>
	<element>
		<node station="Dissertation_model_335" profile="false">
			<position x="235.000000" y="740.000000"/>
				<leaf id="Dissertation_model_2713" align="left"/>
				<leaf id="Dissertation_model_2714" align="right"/>
		</node>
	</element>
	<element>
		<node station="Dissertation_model_335" profile="false">
			<position x="510.000000" y="740.000000"/>
				<leaf id="Dissertation_model_2725" align="left"/>
				<leaf id="Dissertation_model_2726" align="right"/>
		</node>
	</element>
	<element>
		<node station="Dissertation_model_335" profile="false">
			<position x="480.000000" y="790.000000"/>
				<leaf id="Dissertation_model_2737" align="left"/>
				<leaf id="Dissertation_model_2738" align="right"/>
		</node>
	</element>
	<element>
		<node station="Dissertation_model_335" profile="false">
			<position x="560.000000" y="790.000000"/>
				<leaf id="Dissertation_model_2749" align="left"/>
				<leaf id="Dissertation_model_2750" align="right"/>
		</node>
	</element>
	<element>
		<node station="Dissertation_model_335" profile="false">
			<position x="940.000000" y="790.000000"/>
				<leaf id="Dissertation_model_2773" align="left"/>
				<leaf id="Dissertation_model_2774" align="right"/>
		</node>
	</element>
	<element>
		<node station="Dissertation_model_335" profile="false">
			<position x="1030.000000" y="790.000000"/>
				<leaf id="Dissertation_model_2785" align="left"/>
				<leaf id="Dissertation_model_2786" align="right"/>
		</node>
	</element>
	<element>
		<node station="Dissertation_model_335" profile="false">
			<position x="1010.000000" y="740.000000"/>
				<leaf id="Dissertation_model_2797" align="left"/>
				<leaf id="Dissertation_model_2798" align="right"/>
		</node>
	</element>
	<element>
		<node station="Dissertation_model_335" profile="false">
			<position x="1205.000000" y="740.000000"/>
				<leaf id="Dissertation_model_2809" align="left"/>
				<leaf id="Dissertation_model_2810" align="right"/>
		</node>
	</element>
	<element>
		<node station="Dissertation_model_335" profile="false">
			<position x="1240.000000" y="740.000000"/>
				<leaf id="Dissertation_model_2821" align="left"/>
				<leaf id="Dissertation_model_2822" align="right"/>
		</node>
	</element>
	<element>
		<node station="Dissertation_model_999" profile="false">
			<position x="165.000000" y="445.000000"/>
				<leaf id="Dissertation_model_2864" align="left"/>
				<leaf id="Dissertation_model_2865" align="right"/>
		</node>
	</element>
	<element>
		<node station="Dissertation_model_999" profile="false">
			<position x="745.000000" y="445.000000"/>
				<leaf id="Dissertation_model_2878" align="left"/>
				<leaf id="Dissertation_model_2879" align="right"/>
		</node>
	</element>
	<element>
		<node station="Dissertation_model_999" profile="false">
			<position x="785.000000" y="445.000000"/>
				<leaf id="Dissertation_model_2890" align="left"/>
				<leaf id="Dissertation_model_2891" align="right"/>
		</node>
	</element>
	<element>
		<node station="Dissertation_model_756" profile="false">
			<position x="510.000000" y="130.000000"/>
				<leaf id="Dissertation_model_2910" align="left"/>
				<leaf id="Dissertation_model_2911" align="right"/>
		</node>
	</element>
	<element>
		<node station="Dissertation_model_335" profile="false">
			<position x="665.000000" y="890.000000"/>
				<leaf id="Dissertation_model_2941" align="left"/>
				<leaf id="Dissertation_model_2942" align="right"/>
		</node>
	</element>
	<element>
		<node>
			<position x="1340.000000" y="740.000000"/>
				<leaf id="Dissertation_model_3245" align="left"/>
				<leaf id="Dissertation_model_3250" align="right" connector="true"/>
		</node>
	</element>
	<element>
		<node>
			<position x="70.000000" y="445.000000"/>
				<leaf id="Dissertation_model_3262" align="right"/>
				<leaf id="Dissertation_model_3266" align="left" connector="true"/>
		</node>
	</element>
	<element>
		<node>
			<position x="70.000000" y="595.000000"/>
				<leaf id="Dissertation_model_3268" align="right"/>
				<leaf id="Dissertation_model_3272" align="left" connector="true"/>
		</node>
	</element>
	<element>
		<node>
			<position x="1340.000000" y="445.000000"/>
				<leaf id="Dissertation_model_3275" align="left"/>
				<leaf id="Dissertation_model_3285" align="right" connector="true"/>
		</node>
	</element>
	<element>
		<node>
			<position x="1340.000000" y="300.000000"/>
				<leaf id="Dissertation_model_3279" align="left"/>
				<leaf id="Dissertation_model_3286" align="right" connector="true"/>
		</node>
	</element>
	<element>
		<node>
			<position x="1340.000000" y="595.000000"/>
				<leaf id="Dissertation_model_3287" align="left"/>
				<leaf id="Dissertation_model_3292" align="right" connector="true"/>
		</node>
	</element>
	<element>
		<node>
			<position x="70.000000" y="130.000000"/>
				<leaf id="Dissertation_model_3296" align="right"/>
				<leaf id="Dissertation_model_3305" align="left" connector="true"/>
		</node>
	</element>
	<element>
		<node>
			<position x="70.000000" y="300.000000"/>
				<leaf id="Dissertation_model_3300" align="right"/>
				<leaf id="Dissertation_model_3306" align="left" connector="true"/>
		</node>
	</element>
	<element>
		<edge from="Dissertation_model_221" to="Dissertation_model_223" length="157"/>
	</element>
	<element>
		<edge from="Dissertation_model_348" to="Dissertation_model_343" length="60"/>
	</element>
	<element>
		<edge from="Dissertation_model_344" to="Dissertation_model_354" length="12"/>
	</element>
	<element>
		<edge from="Dissertation_model_273" to="Dissertation_model_361" length="48"/>
	</element>
	<element>
		<edge from="Dissertation_model_362" to="Dissertation_model_373" length="59"/>
	</element>
	<element>
		<edge from="Dissertation_model_362" to="Dissertation_model_365" length="59"/>
	</element>
	<element>
		<edge from="Dissertation_model_278" to="Dissertation_model_404" length="3"/>
	</element>
	<element>
		<edge from="Dissertation_model_230" to="Dissertation_model_398" length="46"/>
	</element>
	<element>
		<edge from="Dissertation_model_399" to="Dissertation_model_408" length="62"/>
	</element>
	<element>
		<edge from="Dissertation_model_399" to="Dissertation_model_250" length="85"/>
	</element>
	<element>
		<edge from="Dissertation_model_389" to="Dissertation_model_423" length="60"/>
	</element>
	<element>
		<edge from="Dissertation_model_385" to="Dissertation_model_423" length="60"/>
	</element>
	<element>
		<edge from="Dissertation_model_286" to="Dissertation_model_432" length="3"/>
	</element>
	<element>
		<edge from="Dissertation_model_443" to="Dissertation_model_240" length="46"/>
	</element>
	<element>
		<edge from="Dissertation_model_264" to="Dissertation_model_442" length="62"/>
	</element>
	<element>
		<edge from="Dissertation_model_453" to="Dissertation_model_456" length="12"/>
	</element>
	<element>
		<edge from="Dissertation_model_457" to="Dissertation_model_460" length="60"/>
	</element>
	<element>
		<edge from="Dissertation_model_269" to="Dissertation_model_464" length="157"/>
	</element>
	<element>
		<edge from="Dissertation_model_743" to="Dissertation_model_728" length="62"/>
	</element>
	<element>
		<edge from="Dissertation_model_725" to="Dissertation_model_709" length="62"/>
	</element>
	<element>
		<edge from="Dissertation_model_711" to="Dissertation_model_728" length="46"/>
	</element>
	<element>
		<edge from="Dissertation_model_707" to="Dissertation_model_709" length="85"/>
	</element>
	<element>
		<edge from="Dissertation_model_714" to="Dissertation_model_694" length="62"/>
	</element>
	<element>
		<edge from="Dissertation_model_694" to="Dissertation_model_696" length="62"/>
	</element>
	<element>
		<edge from="Dissertation_model_690" to="Dissertation_model_692" length="46"/>
	</element>
	<element>
		<edge from="Dissertation_model_424" to="Dissertation_model_288" length="48"/>
	</element>
	<element>
		<edge from="Dissertation_model_223" to="Dissertation_model_811" length="36"/>
	</element>
	<element>
		<edge from="Dissertation_model_810" to="Dissertation_model_355" length="37"/>
	</element>
	<element>
		<edge from="Dissertation_model_221" to="Dissertation_model_826" length="36"/>
	</element>
	<element>
		<edge from="Dissertation_model_827" to="Dissertation_model_343" length="36"/>
	</element>
	<element>
		<edge from="Dissertation_model_230" to="Dissertation_model_839" length="40"/>
	</element>
	<element>
		<edge from="Dissertation_model_840" to="Dissertation_model_276" length="40"/>
	</element>
	<element>
		<edge from="Dissertation_model_433" to="Dissertation_model_854" length="41"/>
	</element>
	<element>
		<edge from="Dissertation_model_855" to="Dissertation_model_240" length="40"/>
	</element>
	<element>
		<edge from="Dissertation_model_269" to="Dissertation_model_868" length="36"/>
	</element>
	<element>
		<edge from="Dissertation_model_869" to="Dissertation_model_452" length="37"/>
	</element>
	<element>
		<edge from="Dissertation_model_457" to="Dissertation_model_886" length="36"/>
	</element>
	<element>
		<edge from="Dissertation_model_887" to="Dissertation_model_464" length="36"/>
	</element>
	<element>
		<edge from="Dissertation_model_986" to="Dissertation_model_971" length="62"/>
	</element>
	<element>
		<edge from="Dissertation_model_957" to="Dissertation_model_937" length="62"/>
	</element>
	<element>
		<edge from="Dissertation_model_937" to="Dissertation_model_939" length="62"/>
	</element>
	<element>
		<edge from="Dissertation_model_933" to="Dissertation_model_935" length="76"/>
	</element>
	<element>
		<edge from="Dissertation_model_1139" to="Dissertation_model_1134" length="1865"/>
	</element>
	<element>
		<edge from="Dissertation_model_1127" to="Dissertation_model_1122" length="759"/>
	</element>
	<element>
		<edge from="Dissertation_model_1123" to="Dissertation_model_1082" length="518"/>
	</element>
	<element>
		<edge from="Dissertation_model_1091" to="Dissertation_model_1094" length="3"/>
	</element>
	<element>
		<edge from="Dissertation_model_1219" to="Dissertation_model_1216" length="925"/>
	</element>
	<element>
		<edge from="Dissertation_model_1215" to="Dissertation_model_1212" length="10"/>
	</element>
	<element>
		<edge from="Dissertation_model_1211" to="Dissertation_model_1208" length="10"/>
	</element>
	<element>
		<edge from="Dissertation_model_1207" to="Dissertation_model_1204" length="55"/>
	</element>
	<element>
		<edge from="Dissertation_model_1203" to="Dissertation_model_1200" length="1105"/>
	</element>
	<element>
		<edge from="Dissertation_model_1199" to="Dissertation_model_1196" length="895"/>
	</element>
	<element>
		<edge from="Dissertation_model_1191" to="Dissertation_model_1188" length="530"/>
	</element>
	<element>
		<edge from="Dissertation_model_1187" to="Dissertation_model_1184" length="630"/>
	</element>
	<element>
		<edge from="Dissertation_model_1183" to="Dissertation_model_1180" length="10"/>
	</element>
	<element>
		<edge from="Dissertation_model_1175" to="Dissertation_model_1172" length="1190"/>
	</element>
	<element>
		<edge from="Dissertation_model_1171" to="Dissertation_model_1168" length="2500"/>
	</element>
	<element>
		<edge from="Dissertation_model_1083" to="Dissertation_model_1086" length="812"/>
	</element>
	<element>
		<edge from="Dissertation_model_1118" to="Dissertation_model_1311" length="465"/>
	</element>
	<element>
		<edge from="Dissertation_model_1376" to="Dissertation_model_1411" length="647"/>
	</element>
	<element>
		<edge from="Dissertation_model_954" to="Dissertation_model_1428" length="85"/>
	</element>
	<element>
		<edge from="Dissertation_model_1429" to="Dissertation_model_971" length="46"/>
	</element>
	<element>
		<edge from="Dissertation_model_968" to="Dissertation_model_1428" length="62"/>
	</element>
	<element>
		<edge from="Dissertation_model_238" to="Dissertation_model_442" length="85"/>
	</element>
	<element>
		<edge from="Dissertation_model_366" to="Dissertation_model_1459" length="0"/>
	</element>
	<element>
		<edge from="Dissertation_model_1460" to="Dissertation_model_369" length="534"/>
	</element>
	<element>
		<edge from="Dissertation_model_405" to="Dissertation_model_1471" length="0"/>
	</element>
	<element>
		<edge from="Dissertation_model_1472" to="Dissertation_model_280" length="555"/>
	</element>
	<element>
		<edge from="Dissertation_model_409" to="Dissertation_model_1483" length="0"/>
	</element>
	<element>
		<edge from="Dissertation_model_1484" to="Dissertation_model_232" length="530"/>
	</element>
	<element>
		<edge from="Dissertation_model_252" to="Dissertation_model_1495" length="0"/>
	</element>
	<element>
		<edge from="Dissertation_model_1496" to="Dissertation_model_254" length="507"/>
	</element>
	<element>
		<edge from="Dissertation_model_1508" to="Dissertation_model_262" length="0"/>
	</element>
	<element>
		<edge from="Dissertation_model_1520" to="Dissertation_model_236" length="0"/>
	</element>
	<element>
		<edge from="Dissertation_model_1532" to="Dissertation_model_284" length="0"/>
	</element>
	<element>
		<edge from="Dissertation_model_1544" to="Dissertation_model_388" length="0"/>
	</element>
	<element>
		<edge from="Dissertation_model_1556" to="Dissertation_model_384" length="0"/>
	</element>
	<element>
		<edge from="Dissertation_model_381" to="Dissertation_model_1868" length="539"/>
	</element>
	<element>
		<edge from="Dissertation_model_1869" to="Dissertation_model_1555" length="3"/>
	</element>
	<element>
		<edge from="Dissertation_model_370" to="Dissertation_model_1880" length="539"/>
	</element>
	<element>
		<edge from="Dissertation_model_1881" to="Dissertation_model_1543" length="3"/>
	</element>
	<element>
		<edge from="Dissertation_model_282" to="Dissertation_model_1892" length="560"/>
	</element>
	<element>
		<edge from="Dissertation_model_1893" to="Dissertation_model_1531" length="3"/>
	</element>
	<element>
		<edge from="Dissertation_model_234" to="Dissertation_model_1904" length="513"/>
	</element>
	<element>
		<edge from="Dissertation_model_1905" to="Dissertation_model_1519" length="3"/>
	</element>
	<element>
		<edge from="Dissertation_model_256" to="Dissertation_model_1916" length="250"/>
	</element>
	<element>
		<edge from="Dissertation_model_1917" to="Dissertation_model_1507" length="3"/>
	</element>
	<element>
		<edge from="Dissertation_model_1948" to="Dissertation_model_1938" length="50"/>
	</element>
	<element>
		<edge from="Dissertation_model_1967" to="Dissertation_model_975" length="85"/>
	</element>
	<element>
		<edge from="Dissertation_model_1966" to="Dissertation_model_933" length="58"/>
	</element>
	<element>
		<edge from="Dissertation_model_1967" to="Dissertation_model_1975" length="40"/>
	</element>
	<element>
		<edge from="Dissertation_model_1976" to="Dissertation_model_1938" length="41"/>
	</element>
	<element>
		<edge from="Dissertation_model_1942" to="Dissertation_model_1939" length="3"/>
	</element>
	<element>
		<edge from="Dissertation_model_1167" to="Dissertation_model_1995" length="1000"/>
	</element>
	<element>
		<edge from="Dissertation_model_1994" to="Dissertation_model_1299" length="992"/>
	</element>
	<element>
		<edge from="Dissertation_model_1276" to="Dissertation_model_2007" length="765"/>
	</element>
	<element>
		<edge from="Dissertation_model_2006" to="Dissertation_model_1220" length="235"/>
	</element>
	<element>
		<edge from="Dissertation_model_1195" to="Dissertation_model_2019" length="2500"/>
	</element>
	<element>
		<edge from="Dissertation_model_2018" to="Dissertation_model_1192" length="2470"/>
	</element>
	<element>
		<edge from="Dissertation_model_1179" to="Dissertation_model_2031" length="10"/>
	</element>
	<element>
		<edge from="Dissertation_model_2030" to="Dissertation_model_1176" length="1160"/>
	</element>
	<element>
		<edge from="Dissertation_model_2079" to="Dissertation_model_994" length="0"/>
	</element>
	<element>
		<edge from="Dissertation_model_2110" to="Dissertation_model_1049" length="486"/>
	</element>
	<element>
		<edge from="Dissertation_model_1312" to="Dissertation_model_2123" length="11"/>
	</element>
	<element>
		<edge from="Dissertation_model_732" to="Dissertation_model_2137" length="85"/>
	</element>
	<element>
		<edge from="Dissertation_model_2159" to="Dissertation_model_2149" length="50"/>
	</element>
	<element>
		<edge from="Dissertation_model_2150" to="Dissertation_model_2154" length="3"/>
	</element>
	<element>
		<edge from="Dissertation_model_2137" to="Dissertation_model_2179" length="40"/>
	</element>
	<element>
		<edge from="Dissertation_model_2180" to="Dissertation_model_2149" length="41"/>
	</element>
	<element>
		<edge from="Dissertation_model_2138" to="Dissertation_model_690" length="58"/>
	</element>
	<element>
		<edge from="Dissertation_model_1032" to="Dissertation_model_2193" length="711"/>
	</element>
	<element>
		<edge from="Dissertation_model_2192" to="Dissertation_model_991" length="150"/>
	</element>
	<element>
		<edge from="Dissertation_model_1040" to="Dissertation_model_2217" length="164"/>
	</element>
	<element>
		<edge from="Dissertation_model_2216" to="Dissertation_model_1326" length="146"/>
	</element>
	<element>
		<edge from="Dissertation_model_1044" to="Dissertation_model_2229" length="10"/>
	</element>
	<element>
		<edge from="Dissertation_model_2228" to="Dissertation_model_1041" length="496"/>
	</element>
	<element>
		<edge from="Dissertation_model_1048" to="Dissertation_model_2241" length="174"/>
	</element>
	<element>
		<edge from="Dissertation_model_2240" to="Dissertation_model_1045" length="10"/>
	</element>
	<element>
		<edge from="Dissertation_model_1374" to="Dissertation_model_2253" length="88"/>
	</element>
	<element>
		<edge from="Dissertation_model_1366" to="Dissertation_model_2277" length="670"/>
	</element>
	<element>
		<edge from="Dissertation_model_2276" to="Dissertation_model_1099" length="33"/>
	</element>
	<element>
		<edge from="Dissertation_model_1095" to="Dissertation_model_2288" length="709"/>
	</element>
	<element>
		<edge from="Dissertation_model_2289" to="Dissertation_model_1098" length="40"/>
	</element>
	<element>
		<edge from="Dissertation_model_1087" to="Dissertation_model_2300" length="40"/>
	</element>
	<element>
		<edge from="Dissertation_model_2301" to="Dissertation_model_1090" length="345"/>
	</element>
	<element>
		<edge from="Dissertation_model_1143" to="Dissertation_model_2312" length="515"/>
	</element>
	<element>
		<edge from="Dissertation_model_2313" to="Dissertation_model_1138" length="144"/>
	</element>
	<element>
		<edge from="Dissertation_model_1119" to="Dissertation_model_2324" length="196"/>
	</element>
	<element>
		<edge from="Dissertation_model_1325" to="Dissertation_model_1033" length="281"/>
	</element>
	<element>
		<edge from="Dissertation_model_1135" to="Dissertation_model_2357" length="2500"/>
	</element>
	<element>
		<edge from="Dissertation_model_2358" to="Dissertation_model_1130" length="3000"/>
	</element>
	<element>
		<edge from="Dissertation_model_1131" to="Dissertation_model_2369" length="1717"/>
	</element>
	<element>
		<edge from="Dissertation_model_2370" to="Dissertation_model_1126" length="524"/>
	</element>
	<element>
		<edge from="Dissertation_model_2325" to="Dissertation_model_2336" length="796"/>
	</element>
	<element>
		<edge from="Dissertation_model_977" to="Dissertation_model_2384" length="0"/>
	</element>
	<element>
		<edge from="Dissertation_model_2385" to="Dissertation_model_980" length="512"/>
	</element>
	<element>
		<edge from="Dissertation_model_2397" to="Dissertation_model_984" length="0"/>
	</element>
	<element>
		<edge from="Dissertation_model_982" to="Dissertation_model_2408" length="590"/>
	</element>
	<element>
		<edge from="Dissertation_model_2409" to="Dissertation_model_2396" length="3"/>
	</element>
	<element>
		<edge from="Dissertation_model_2425" to="Dissertation_model_944" length="544"/>
	</element>
	<element>
		<edge from="Dissertation_model_941" to="Dissertation_model_2436" length="0"/>
	</element>
	<element>
		<edge from="Dissertation_model_2437" to="Dissertation_model_2424" length="3"/>
	</element>
	<element>
		<edge from="Dissertation_model_946" to="Dissertation_model_2448" length="524"/>
	</element>
	<element>
		<edge from="Dissertation_model_2449" to="Dissertation_model_952" length="0"/>
	</element>
	<element>
		<edge from="Dissertation_model_959" to="Dissertation_model_2460" length="0"/>
	</element>
	<element>
		<edge from="Dissertation_model_2461" to="Dissertation_model_962" length="547"/>
	</element>
	<element>
		<edge from="Dissertation_model_2473" to="Dissertation_model_966" length="0"/>
	</element>
	<element>
		<edge from="Dissertation_model_964" to="Dissertation_model_2484" length="544"/>
	</element>
	<element>
		<edge from="Dissertation_model_2485" to="Dissertation_model_2472" length="3"/>
	</element>
	<element>
		<edge from="Dissertation_model_734" to="Dissertation_model_2504" length="0"/>
	</element>
	<element>
		<edge from="Dissertation_model_2505" to="Dissertation_model_737" length="512"/>
	</element>
	<element>
		<edge from="Dissertation_model_2517" to="Dissertation_model_741" length="0"/>
	</element>
	<element>
		<edge from="Dissertation_model_739" to="Dissertation_model_2528" length="590"/>
	</element>
	<element>
		<edge from="Dissertation_model_2529" to="Dissertation_model_2516" length="3"/>
	</element>
	<element>
		<edge from="Dissertation_model_698" to="Dissertation_model_2540" length="0"/>
	</element>
	<element>
		<edge from="Dissertation_model_2541" to="Dissertation_model_2552" length="3"/>
	</element>
	<element>
		<edge from="Dissertation_model_2553" to="Dissertation_model_701" length="544"/>
	</element>
	<element>
		<edge from="Dissertation_model_703" to="Dissertation_model_2564" length="521"/>
	</element>
	<element>
		<edge from="Dissertation_model_2565" to="Dissertation_model_705" length="3"/>
	</element>
	<element>
		<edge from="Dissertation_model_716" to="Dissertation_model_2576" length="0"/>
	</element>
	<element>
		<edge from="Dissertation_model_2577" to="Dissertation_model_719" length="547"/>
	</element>
	<element>
		<edge from="Dissertation_model_2589" to="Dissertation_model_723" length="0"/>
	</element>
	<element>
		<edge from="Dissertation_model_721" to="Dissertation_model_2600" length="544"/>
	</element>
	<element>
		<edge from="Dissertation_model_2601" to="Dissertation_model_2588" length="3"/>
	</element>
	<element>
		<edge from="Dissertation_model_753" to="Dissertation_model_2654" length="0"/>
	</element>
	<element>
		<edge from="Dissertation_model_2337" to="Dissertation_model_751" length="150"/>
	</element>
	<element>
		<edge from="Dissertation_model_730" to="Dissertation_model_2672" length="3"/>
	</element>
	<element>
		<edge from="Dissertation_model_2673" to="Dissertation_model_2684" length="100"/>
	</element>
	<element>
		<edge from="Dissertation_model_2685" to="Dissertation_model_746" length="0"/>
	</element>
	<element>
		<edge from="Dissertation_model_300" to="Dissertation_model_2700" length="0"/>
	</element>
	<element>
		<edge from="Dissertation_model_2701" to="Dissertation_model_2713" length="100"/>
	</element>
	<element>
		<edge from="Dissertation_model_2714" to="Dissertation_model_219" length="3"/>
	</element>
	<element>
		<edge from="Dissertation_model_225" to="Dissertation_model_2725" length="115"/>
	</element>
	<element>
		<edge from="Dissertation_model_2726" to="Dissertation_model_228" length="3"/>
	</element>
	<element>
		<edge from="Dissertation_model_355" to="Dissertation_model_2737" length="185"/>
	</element>
	<element>
		<edge from="Dissertation_model_2738" to="Dissertation_model_271" length="3"/>
	</element>
	<element>
		<edge from="Dissertation_model_273" to="Dissertation_model_2749" length="25"/>
	</element>
	<element>
		<edge from="Dissertation_model_2750" to="Dissertation_model_276" length="58"/>
	</element>
	<element>
		<edge from="Dissertation_model_433" to="Dissertation_model_2773" length="28"/>
	</element>
	<element>
		<edge from="Dissertation_model_2774" to="Dissertation_model_288" length="56"/>
	</element>
	<element>
		<edge from="Dissertation_model_290" to="Dissertation_model_2785" length="3"/>
	</element>
	<element>
		<edge from="Dissertation_model_2786" to="Dissertation_model_452" length="185"/>
	</element>
	<element>
		<edge from="Dissertation_model_242" to="Dissertation_model_2797" length="3"/>
	</element>
	<element>
		<edge from="Dissertation_model_2798" to="Dissertation_model_267" length="115"/>
	</element>
	<element>
		<edge from="Dissertation_model_465" to="Dissertation_model_2809" length="3"/>
	</element>
	<element>
		<edge from="Dissertation_model_2810" to="Dissertation_model_2821" length="100"/>
	</element>
	<element>
		<edge from="Dissertation_model_2822" to="Dissertation_model_293" length="0"/>
	</element>
	<element>
		<edge from="Dissertation_model_996" to="Dissertation_model_2864" length="100"/>
	</element>
	<element>
		<edge from="Dissertation_model_2865" to="Dissertation_model_931" length="3"/>
	</element>
	<element>
		<edge from="Dissertation_model_973" to="Dissertation_model_2878" length="3"/>
	</element>
	<element>
		<edge from="Dissertation_model_2879" to="Dissertation_model_2890" length="100"/>
	</element>
	<element>
		<edge from="Dissertation_model_2891" to="Dissertation_model_989" length="0"/>
	</element>
	<element>
		<edge from="Dissertation_model_2655" to="Dissertation_model_2910" length="100"/>
	</element>
	<element>
		<edge from="Dissertation_model_2911" to="Dissertation_model_688" length="3"/>
	</element>
	<element>
		<edge from="Dissertation_model_2252" to="Dissertation_model_1368" length="460"/>
	</element>
	<element>
		<edge from="Dissertation_model_374" to="Dissertation_model_2941" length="0"/>
	</element>
	<element>
		<edge from="Dissertation_model_2942" to="Dissertation_model_380" length="534"/>
	</element>
	<element>
		<edge from="Dissertation_model_295" to="Dissertation_model_3245" length="75"/>
	</element>
	<element>
		<edge from="Dissertation_model_2078" to="Dissertation_model_3262" length="75"/>
	</element>
	<element>
		<edge from="Dissertation_model_1300" to="Dissertation_model_3268" length="75"/>
	</element>
	<element>
		<edge from="Dissertation_model_2111" to="Dissertation_model_3275" length="75"/>
	</element>
	<element>
		<edge from="Dissertation_model_1412" to="Dissertation_model_3279" length="74"/>
	</element>
	<element>
		<edge from="Dissertation_model_1275" to="Dissertation_model_3287" length="100"/>
	</element>
	<element>
		<edge from="Dissertation_model_1142" to="Dissertation_model_3300" length="5"/>
	</element>
	<element>
		<edge from="Dissertation_model_2122" to="Dissertation_model_3296" length="6"/>
	</element>
	<element>
		<edge from="Dissertation_model_3250" to="Dissertation_model_3292" length="0"/>
	</element>
	<element>
		<edge from="Dissertation_model_3266" to="Dissertation_model_3272" length="0"/>
	</element>
	<element>
		<edge from="Dissertation_model_3285" to="Dissertation_model_3286" length="0"/>
	</element>
	<element>
		<edge from="Dissertation_model_3305" to="Dissertation_model_3306" length="0"/>
	</element>
	<element>
		<signal element="Dissertation_model_262" type="1" side="right"/>
	</element>
	<element>
		<signal element="Dissertation_model_295" type="2" side="right"/>
	</element>
	<element>
		<signal element="Dissertation_model_374" type="2" side="right"/>
	</element>
	<element>
		<signal element="Dissertation_model_366" type="2" side="right"/>
	</element>
	<element>
		<signal element="Dissertation_model_405" type="2" side="right"/>
	</element>
	<element>
		<signal element="Dissertation_model_409" type="2" side="right"/>
	</element>
	<element>
		<signal element="Dissertation_model_252" type="2" side="right"/>
	</element>
	<element>
		<signal element="Dissertation_model_384" type="2" side="right"/>
	</element>
	<element>
		<signal element="Dissertation_model_388" type="2" side="right"/>
	</element>
	<element>
		<signal element="Dissertation_model_284" type="1" side="right"/>
	</element>
	<element>
		<signal element="Dissertation_model_236" type="2" side="right"/>
	</element>
	<element>
		<signal element="Dissertation_model_698" type="1" side="right"/>
	</element>
	<element>
		<signal element="Dissertation_model_716" type="1" side="right"/>
	</element>
	<element>
		<signal element="Dissertation_model_723" type="1" side="right"/>
	</element>
	<element>
		<signal element="Dissertation_model_734" type="1" side="right"/>
	</element>
	<element>
		<signal element="Dissertation_model_741" type="1" side="right"/>
	</element>
	<element>
		<signal element="Dissertation_model_748" type="2" side="right"/>
	</element>
	<element>
		<signal element="Dissertation_model_751" type="2" side="right"/>
	</element>
	<element>
		<signal element="Dissertation_model_941" type="1" side="right"/>
	</element>
	<element>
		<signal element="Dissertation_model_952" type="1" side="right"/>
	</element>
	<element>
		<signal element="Dissertation_model_959" type="1" side="right"/>
	</element>
	<element>
		<signal element="Dissertation_model_966" type="1" side="right"/>
	</element>
	<element>
		<signal element="Dissertation_model_977" type="1" side="right"/>
	</element>
	<element>
		<signal element="Dissertation_model_984" type="1" side="right"/>
	</element>
	<element>
		<signal element="Dissertation_model_991" type="2" side="right"/>
	</element>
	<element>
		<signal element="Dissertation_model_298" type="2" side="right"/>
	</element>
	<element>
		<signal element="Dissertation_model_2078" type="2" side="right"/>
	</element>
	<element>
		<signal element="Dissertation_model_705" type="1" side="right"/>
	</element>
</otml>
